IndianNameGenerator/Names.py
IndianNameGenerator/__init__.py
IndianNameGenerator-4.0.0.dist-info/LICENSE
IndianNameGenerator-4.0.0.dist-info/METADATA
IndianNameGenerator-4.0.0.dist-info/WHEEL
IndianNameGenerator-4.0.0.dist-info/top_level.txt
IndianNameGenerator-4.0.0.dist-info/RECORD
