Metadata-Version: 2.1
Name: IndianNameGenerator
Version: 4.0.0
Summary: A quick way to get indian names
Home-page: https://github.com/OnkarGavali/indian-name-generator
Author: OnkarGavali
Author-email: onkargavali1561@gmail.com
License: MIT
Platform: UNKNOWN
Classifier: License :: OSI Approved :: MIT License
Requires-Python: >=3.0
